gprof2dot.py
yelp_gprof2dot-1.2.0.dist-info/DESCRIPTION.rst
yelp_gprof2dot-1.2.0.dist-info/METADATA
yelp_gprof2dot-1.2.0.dist-info/RECORD
yelp_gprof2dot-1.2.0.dist-info/WHEEL
yelp_gprof2dot-1.2.0.dist-info/entry_points.txt
yelp_gprof2dot-1.2.0.dist-info/metadata.json
yelp_gprof2dot-1.2.0.dist-info/top_level.txt
