Metadata-Version: 2.0
Name: yelp-gprof2dot
Version: 1.2.0
Summary: Generate a dot graph from the output of python profilers.
Home-page: https://github.com/Yelp/gprof2dot
Author: Yelp Performance Team
Author-email: UNKNOWN
License: LGPL
Platform: UNKNOWN
